{"name":"Traduccion de ingles a espanhol","id":"google-translate;traduccion-de-ingles-a-espanhol","testSteps":[{"number":1,"description":"Given que Christopher quiere traducir una palabra","duration":12305,"startTime":"2019-08-08T13:09:01.836-05:00[America/Bogota]","screenshots":[{"screenshot":"e85af1470c6c4b82630406bb658eca5689a53b7468b2e68e09accd52e92faed6.png"}],"result":"SUCCESS","precondition":false,"children":[{"number":2,"description":"Christopher abre el navegador en Google Home Page","duration":5886,"startTime":"2019-08-08T13:09:02.275-05:00[America/Bogota]","screenshots":[{"screenshot":"edbf87e3b3e6930fb052b2783857c9a0800e412302c68ac066958f03faaba326.png"}],"result":"SUCCESS","precondition":false,"children":[{"number":3,"description":"Christopher opens the Google home page","duration":5539,"startTime":"2019-08-08T13:09:02.306-05:00[America/Bogota]","screenshots":[{"screenshot":"8a1ae4cceb9dc006cd5199e993f7950472d1dc36eb3e7a8d04c71ff554c310fb.png"}],"result":"SUCCESS","precondition":false}]},{"number":4,"description":"Christopher clicks on GoogleAppsButton","duration":1143,"startTime":"2019-08-08T13:09:08.256-05:00[America/Bogota]","screenshots":[{"screenshot":"8a1ae4cceb9dc006cd5199e993f7950472d1dc36eb3e7a8d04c71ff554c310fb.png"},{"screenshot":"276b5cade7ea36fdaa8eae7e6b2bf740c7404178747e3484980d131b7946b7f8.png"}],"result":"SUCCESS","precondition":false},{"number":5,"description":"Christopher clicks on GoogleTranslateOption","duration":4473,"startTime":"2019-08-08T13:09:09.401-05:00[America/Bogota]","screenshots":[{"screenshot":"276b5cade7ea36fdaa8eae7e6b2bf740c7404178747e3484980d131b7946b7f8.png"},{"screenshot":"e85af1470c6c4b82630406bb658eca5689a53b7468b2e68e09accd52e92faed6.png"}],"result":"SUCCESS","precondition":false}]},{"number":6,"description":"When el traduce la plabra cheese de ingles a espanhol","duration":4423,"startTime":"2019-08-08T13:09:14.142-05:00[America/Bogota]","screenshots":[{"screenshot":"0240f6db1a99df8fc8f4104322eb5e77d612a3f8de5561a7260dfc4d46b0aecf.png"},{"screenshot":"6d90b039e8e66a34a845e3f1b76d8a5ff5d3dbbbc1ca01c8fd485d91050c5da3.png"}],"result":"SUCCESS","precondition":false,"children":[{"number":7,"description":"Christopher clicks on Source language button","duration":849,"startTime":"2019-08-08T13:09:14.450-05:00[America/Bogota]","screenshots":[{"screenshot":"0595df556a073eceed5bef5e764c0417b1d50a8ef2301b4f5309578dab319570.png"}],"result":"SUCCESS","precondition":false},{"number":8,"description":"Christopher clicks on Source language","duration":851,"startTime":"2019-08-08T13:09:15.301-05:00[America/Bogota]","screenshots":[{"screenshot":"fb6bc27475ee20bdf12adac6b9498bf46388b9d982f11bfe1ddb9ac7792ca981.png"},{"screenshot":"efe5b25e02145dc9e5ec7a92325b5c6e205b0eb5a46c4d059c044a71295a5a7c.png"}],"result":"SUCCESS","precondition":false},{"number":9,"description":"Christopher clicks on Target language button","duration":682,"startTime":"2019-08-08T13:09:16.154-05:00[America/Bogota]","screenshots":[{"screenshot":"0f63d480ac0842d98e18fcac2ec9e7be005f0722481b935e2b5f1f40b2854f65.png"},{"screenshot":"35dcfc721ccb48a989c4bce41b470350b6ab47f4a5bba72593e8016d23f5572e.png"}],"result":"SUCCESS","precondition":false},{"number":10,"description":"Christopher clicks on Source language","duration":661,"startTime":"2019-08-08T13:09:16.837-05:00[America/Bogota]","screenshots":[{"screenshot":"35dcfc721ccb48a989c4bce41b470350b6ab47f4a5bba72593e8016d23f5572e.png"},{"screenshot":"efe5b25e02145dc9e5ec7a92325b5c6e205b0eb5a46c4d059c044a71295a5a7c.png"}],"result":"SUCCESS","precondition":false},{"number":11,"description":"Christopher enters \u0027cheese\u0027 into Source language textarea","duration":766,"startTime":"2019-08-08T13:09:17.500-05:00[America/Bogota]","screenshots":[{"screenshot":"efe5b25e02145dc9e5ec7a92325b5c6e205b0eb5a46c4d059c044a71295a5a7c.png"},{"screenshot":"68874486e1a16af8514811d47719a8caf1fb8665dda8ab0d8f8d8f247d432822.png"}],"result":"SUCCESS","precondition":false}]},{"number":12,"description":"Then el podra ver la palabra queso en la pantalla","duration":1393,"startTime":"2019-08-08T13:09:18.565-05:00[America/Bogota]","screenshots":[{"screenshot":"09eb8fdabf7ad4923b2fecd27906455d7807ee61db6942139f2dd6bd597dbe31.png"}],"result":"SUCCESS","precondition":false,"children":[{"number":13,"description":"Then la palabra should be \u0027queso\u0027","duration":615,"startTime":"2019-08-08T13:09:19.070-05:00[America/Bogota]","screenshots":[{"screenshot":"e352ef3eff69ecf8d664ebe3dbb11ee3715d985b2b05f056ed9caeb1bd2c8af4.png"},{"screenshot":"09eb8fdabf7ad4923b2fecd27906455d7807ee61db6942139f2dd6bd597dbe31.png"}],"result":"SUCCESS","precondition":false}]}],"userStory":{"id":"google-translate","storyName":"Google Translate","path":"src/test/resoruces/features/GoogleTranslate.feature","narrative":"  Christopher quiere usar translate para traducir palabras entre diferentes lenguajes","type":"feature"},"featureTag":{"name":"Features/Google Translate","type":"feature"},"title":"Traduccion de ingles a espanhol","tags":[{"name":"Google translate","type":"feature"}],"startTime":"2019-08-08T13:08:59.719-05:00[America/Bogota]","duration":20341,"projectKey":"","sessionId":"ad686581bf22b9800cbd1721c8a1cf36","driver":"chrome","manual":false,"testSource":"Cucumber","result":"SUCCESS"}